pyrefox/__init__.py
pyrefox/main.py
pyrefox/py.typed
pyrefox/types.py
pyrefox/utils.py
pyrefox/models/__init__.py
pyrefox/models/enums.py
pyrefox/models/extensions.py
pyrefox/orm/__init__.py
pyrefox/orm/_sql.py
pyrefox/orm/_types.py
pyrefox/orm/content_prefs.py
pyrefox/orm/cookies.py
pyrefox/orm/favicons.py
pyrefox/orm/formhistory.py
pyrefox/orm/permissions.py
pyrefox/orm/places.py
pyrefox/orm/protections.py
pyrefox/orm/storage.py
pyrefox/orm/storage_sync.py
pyrefox/orm/storage_sync_v2.py
pyrefox/orm/webappsstore.py
pyrefox-0.0.1.dev2.dist-info/LICENSE
pyrefox-0.0.1.dev2.dist-info/METADATA
pyrefox-0.0.1.dev2.dist-info/WHEEL
pyrefox-0.0.1.dev2.dist-info/top_level.txt
pyrefox-0.0.1.dev2.dist-info/RECORD
